{
"type": "FeatureCollection",
"name": "sites_ex",
"crs": { "type": "name", "properties": { "name": "urn:ogc:def:crs:OGC:1.3:CRS84" } },
"features": [
{ "type": "Feature", "properties": { "id": 1 }, "geometry": { "type": "Point", "coordinates": [ -119.465257404720475, 37.935675721551256 ] } },
{ "type": "Feature", "properties": { "id": 2 }, "geometry": { "type": "Point", "coordinates": [ -119.445156052896152, 37.968012678833858 ] } },
{ "type": "Feature", "properties": { "id": 3 }, "geometry": { "type": "Point", "coordinates": [ -119.399272532427574, 37.986803072930513 ] } },
{ "type": "Feature", "properties": { "id": 4 }, "geometry": { "type": "Point", "coordinates": [ -119.426802644708715, 38.004282509299493 ] } },
{ "type": "Feature", "properties": { "id": 5 }, "geometry": { "type": "Point", "coordinates": [ -119.401894447882924, 37.923003130183744 ] } },
{ "type": "Feature", "properties": { "id": 6 }, "geometry": { "type": "Point", "coordinates": [ -119.428987574254847, 37.912078482453133 ] } },
{ "type": "Feature", "properties": { "id": 7 }, "geometry": { "type": "Point", "coordinates": [ -119.352078054231342, 37.87449769425983 ] } },
{ "type": "Feature", "properties": { "id": 8 }, "geometry": { "type": "Point", "coordinates": [ -119.309253435127346, 37.865320990166119 ] } },
{ "type": "Feature", "properties": { "id": 10 }, "geometry": { "type": "Point", "coordinates": [ -119.27167264693405, 37.815941582423754 ] } },
{ "type": "Feature", "properties": { "id": 11 }, "geometry": { "type": "Point", "coordinates": [ -119.254193210565063, 37.880615496988973 ] } },
{ "type": "Feature", "properties": { "id": 12 }, "geometry": { "type": "Point", "coordinates": [ -119.411945123795093, 38.054098902951075 ] } },
{ "type": "Feature", "properties": { "id": 13 }, "geometry": { "type": "Point", "coordinates": [ -119.365187631508078, 38.016518114757773 ] } },
{ "type": "Feature", "properties": { "id": 14 }, "geometry": { "type": "Point", "coordinates": [ -119.383978025604719, 38.000349636116468 ] } }
]
}
